{"hash":"b8170d693042ab71b5feb17a77a124f350e9671c","data":{"tag":{"title":"plant species diversity","belongsTo":{"totalCount":1,"pageInfo":{"totalPages":1,"currentPage":1},"edges":[{"node":{"__typename":"News","title":"Asian dogwood Cornus kousa","startDate":"15 Jun 2020","path":"/news/cornus-kousa/","slug":"cornus-kousa","summary":"Our paper on Asian dogwood species diversity accepted in Ecology and Evolution.","tags":[{"title":"dogwoods"},{"title":"plant species diversity"},{"title":"population genetics"},{"title":"evolutionary history"}]}}]}}},"context":{}}